django_stream_logging/__init__.py
django_stream_logging/commands.py
django_stream_logging/formatters.py
django_stream_logging/handlers.py
django_stream_logging/mixins.py
django_stream_logging/views.py
django_stream_logging-0.2.1.dist-info/LICENSE
django_stream_logging-0.2.1.dist-info/METADATA
django_stream_logging-0.2.1.dist-info/WHEEL
django_stream_logging-0.2.1.dist-info/top_level.txt
django_stream_logging-0.2.1.dist-info/RECORD
