Metadata-Version: 2.1
Name: django-stream-logging
Version: 0.2.1
Summary: Django stream logging classes for views and commands.
Home-page: https://github.com/cristhianCEM/django-stream-logging
Author: cristianCEM
Author-email: cristianbcer27@gmail.com
License: MIT
Keywords: Django,logging,stream,views,commands
Classifier: Environment :: Web Environment
Classifier: Framework :: Django
Classifier: Framework :: Django :: 5.0
Classifier: Intended Audience :: Developers
Classifier: License :: OSI Approved :: MIT License
Classifier: Operating System :: OS Independent
Classifier: Programming Language :: Python
Classifier: Programming Language :: Python :: 3
Requires-Python: >=3.10
License-File: LICENSE
Requires-Dist: Django>=5.0.0
Requires-Dist: colorlog>=5.0.0
